colority/__init__.py
colority/ansi.py
colority/ansitowin32.py
colority/initialise.py
colority/win32.py
colority/winterm.py
colority/tests/__init__.py
colority/tests/ansi_test.py
colority/tests/ansitowin32_test.py
colority/tests/initialise_test.py
colority/tests/isatty_test.py
colority/tests/utils.py
colority/tests/winterm_test.py
colority-1.0.1.dist-info/METADATA
colority-1.0.1.dist-info/WHEEL
colority-1.0.1.dist-info/top_level.txt
colority-1.0.1.dist-info/RECORD
