Metadata-Version: 2.1
Name: colority
Version: 1.0.1
Summary: Wonderful colorizer for text in terminal.
Author: gagzui
Classifier: Programming Language :: Python :: 3
Classifier: License :: OSI Approved :: MIT License
Classifier: Operating System :: OS Independent
Requires-Python: >=3.6
